MANIFEST.in
README
__init__.py
__pkginfo__.py
entities.py
hooks.py
logformat.py
schema.py
setup.py
site_cubicweb.py
./__init__.py
./__pkginfo__.py
./entities.py
./hooks.py
./logformat.py
./schema.py
./site_cubicweb.py
./test/pytestconf.py
./test/realdb_test_apycot.py
./test/test_apycot.py
./test/unittest_apycot.py
./test/unittest_entities.py
./test/unittest_hooks.py
./test/unittest_utils.py
./test/utils.py
./views/__init__.py
./views/bot.py
./views/facets.py
./views/primary.py
./views/reports.py
./views/rss.py
./views/secondary.py
./views/tracker.py
cubicweb_apycot.egg-info/PKG-INFO
cubicweb_apycot.egg-info/SOURCES.txt
cubicweb_apycot.egg-info/dependency_links.txt
cubicweb_apycot.egg-info/requires.txt
cubicweb_apycot.egg-info/top_level.txt
data/cubes.apycot.css
data/cubes.apycot.js
data/feed-logo.png
data/feed-logo.svg
doc/apycot_processes_en.dia
i18n/en.po
i18n/es.po
i18n/fr.po
migration/0.2.0_Any.py
migration/1.0.1_Any.py
migration/1.0.4_Any.py
migration/1.0.7_Any.py
migration/1.2.0_Any.py
migration/1.3.0_Any.py
migration/1.4.0_Any.py
migration/1.4.1_Any.py
migration/1.4.3_Any.py
migration/1.5.0_Any.py
migration/1.6.0_Any.py
migration/1.9.0_Any.py
migration/postcreate.py
migration/precreate.py
schema/_regproc.postgres.sql
test/test_apycot.py
views/__init__.py
views/bot.py
views/facets.py
views/primary.py
views/reports.py
views/rss.py
views/secondary.py
views/tracker.py
wdoc/ChangeLog_en
wdoc/ChangeLog_fr
wdoc/apycot_automation_en.rst
wdoc/apycot_checker_en.rst
wdoc/apycot_en.rst
wdoc/apycot_links_en.rst
wdoc/apycot_step_by_step_fr.rst
wdoc/apycot_test_configuration_en.rst
wdoc/toc.xml
wdoc/images/apycot_processes_en.png