Metadata-Version: 1.0
Name: cubicweb-apycot
Version: 1.9.0
Summary: Continuous testing / integration tool for the CubicWeb framework
Home-page: http://www.cubicweb.org/project/cubicweb-apycot
Author: Logilab
Author-email: contact@logilab.fr
License: GPL
Platform: UNKNOWN
